<dc:title>Introduction to Scheduling with Microsoft Project: Best Practices from Project MVPs</dc:title>
<dc:rights>All rights reserved</dc:rights>
<dc:language>en-US</dc:language>

<dc:creator opf:file-as="Lewis, Cindy" opf:role="aut">Cindy Lewis</dc:creator>
<dc:creator opf:file-as="Runcie, Tim" opf:role="ctb">Tim Runcie</dc:creator>
<dc:creator opf:file-as="Lehnert, Ellen" opf:role="ctb">Ellen Lehnert</dc:creator>
<dc:creator opf:file-as="Jacobson-Swartfager, Jeff" opf:role="bkd">Jeff Jacobson-Swartfager</dc:creator>

<dc:contributor opf:file-as="Phillips-Mead, Jesse" opf:role="ctb">Jesse Phillips-Mead</dc:contributor>
<dc:contributor opf:file-as="Greensky, Pam" opf:role="pmn">Pam Greensky</dc:contributor>

<dc:publisher>Advisicon Press</dc:publisher>
